{
  "primary_pipeline" : "686918f2-9822-4222-972e-f0a0bf716afe",
  "pipelines" : [ {
    "nodes" : [ {
      "outputs" : [ {
        "id" : "1c9e34da-1fe9-4469-8c8b-18ae5c50f2cd",
        "app_data" : {
          "datastage" : {
            "is_source_of_link" : "2e2cf8a0-149b-4f68-879a-18d4b49904c1"
          },
          "ui_data" : {
            "label" : "outPort",
            "cardinality" : {
              "min" : 0,
              "max" : 2147483647
            }
          },
          "additionalProperties" : {
            "enableAcp" : true
          }
        },
        "schema_ref" : "5bb144de-ef15-418b-9d13-e9aa5c756f0c",
        "parameters" : {
          "reject_uses" : "rows",
          "buf_free_run" : 50,
          "buf_mode" : "default",
          "queue_upper_size" : 0,
          "max_mem_buf_size" : 3145728,
          "reject_number" : 0,
          "disk_write_inc" : 1048576
        }
      } ],
      "op" : "ODBCConnectorPX",
      "connection" : {
        "ref" : "72f937ae-333f-4dbe-a518-1598956e3868",
        "properties" : {
          "currentOutputLinkType" : "PRIMARY",
          "sql.select_statement.tables.table" : "",
          "session.isolation_level" : "read_uncommitted",
          "transaction.end_of_wave" : "none",
          "outputAcpShouldHide" : true,
          "enableSchemalessDesign" : false,
          "session.autocommit_mode" : "off",
          "node_number" : 0,
          "session.code_page" : "default",
          "node_count" : 1,
          "sql.select_statement.read_statement_from_file" : false,
          "sql.select_statement.where_clause" : "",
          "sql.select_statement.columns.column" : "",
          "session.pass_lob_locator" : false,
          "limit_rows" : false,
          "session.schema_reconciliation.fail_on_size_mismatch" : true,
          "enableFlowAcpControl" : true,
          "sql.select_statement" : "select saleskey, productkey, quantitysold, salestotal\nfrom em.factsales\nwhere \ndatekey >= #datekey_start# and datekey <= #datekey_end#",
          "session.array_size" : 2000,
          "sql.enable_partitioning" : false,
          "session.schema_reconciliation.fail_on_type_mismatch" : true,
          "before_after" : false,
          "generate_sql" : false,
          "transaction.record_count" : 2000,
          "enable_quoted_i_ds" : false
        },
        "name" : "RDS postgres-dev_cp4d"
      },
      "id" : "a7710207-a64e-4b8c-8b6c-d30513837564",
      "type" : "binding",
      "app_data" : {
        "datastage" : { },
        "ui_data" : {
          "image" : "/data-intg/flows/graphics/palette/ODBCConnectorPX.svg",
          "x_pos" : 47.519999999999996,
          "label" : "odbcFactsales",
          "y_pos" : 31.68
        }
      },
      "parameters" : {
        "combinability" : "auto",
        "output_count" : 1,
        "input_count" : 0,
        "execmode" : "default_par",
        "preserve" : -3,
        "allow_column_mapping" : false
      }
    }, {
      "outputs" : [ {
        "id" : "cf94dfd4-f02c-4a94-8920-9e010fc24665",
        "app_data" : {
          "datastage" : {
            "is_source_of_link" : "d0577937-2356-40b4-aeba-dd3d09262718"
          },
          "ui_data" : {
            "label" : "outPort",
            "cardinality" : {
              "min" : 1,
              "max" : 1
            }
          }
        },
        "schema_ref" : "af46f22d-697d-411f-8808-72870504e1d8",
        "parameters" : {
          "buf_free_run" : 50,
          "queue_upper_size" : 0,
          "max_mem_buf_size" : 3145728,
          "disk_write_inc" : 1048576
        }
      } ],
      "op" : "PxJoin",
      "inputs" : [ {
        "links" : [ {
          "node_id_ref" : "a7710207-a64e-4b8c-8b6c-d30513837564",
          "type_attr" : "PRIMARY",
          "id" : "2e2cf8a0-149b-4f68-879a-18d4b49904c1",
          "app_data" : {
            "datastage" : { },
            "ui_data" : {
              "decorations" : [ {
                "image" : "/data-intg/flows/graphics/flows/link-output-handle--default-selected.svg",
                "temporary" : false,
                "outline" : false,
                "distance" : 0,
                "x_pos" : -10,
                "id" : "dec-3",
                "position" : "source",
                "y_pos" : -10,
                "class_name" : "linkStartImage"
              }, {
                "image" : "/data-intg/flows/graphics/flows/link-marking--auto-partitioning.svg",
                "temporary" : false,
                "outline" : false,
                "distance" : 2,
                "width" : 50,
                "tooltip" : "Auto-partition",
                "x_pos" : -15,
                "id" : "dec-6R",
                "position" : "middle",
                "y_pos" : 4,
                "height" : 50
              }, {
                "temporary" : false,
                "label_single_line" : true,
                "label_align" : "center",
                "tooltip" : "factsales",
                "x_pos" : 0,
                "label" : "factsales",
                "label_allow_return_key" : "save",
                "width" : 110,
                "label_editable" : true,
                "id" : "dec-8",
                "position" : "middle",
                "y_pos" : -20,
                "height" : 20
              } ],
              "class_name" : "linkStyle__runMetricsLinkDefaultStyle___ixW31"
            }
          },
          "link_name" : "factsales",
          "port_id_ref" : "1c9e34da-1fe9-4469-8c8b-18ae5c50f2cd"
        } ],
        "id" : "4b4f5d6b-89bb-41ff-8ea5-c21beda8f278",
        "app_data" : {
          "datastage" : { },
          "ui_data" : {
            "label" : "inPort",
            "cardinality" : {
              "min" : 2,
              "max" : 2147483646
            }
          }
        },
        "schema_ref" : "5bb144de-ef15-418b-9d13-e9aa5c756f0c",
        "parameters" : {
          "part_coll" : "part_type",
          "runtime_column_propagation" : 0
        }
      }, {
        "links" : [ {
          "node_id_ref" : "74315f23-5ba2-444a-8f0b-e15d5455dfc6",
          "type_attr" : "PRIMARY",
          "id" : "10734b55-e718-49a2-a43b-d5ddfb209481",
          "app_data" : {
            "datastage" : { },
            "ui_data" : {
              "decorations" : [ {
                "image" : "/data-intg/flows/graphics/flows/link-output-handle--default-selected.svg",
                "temporary" : false,
                "outline" : false,
                "distance" : 0,
                "x_pos" : -10,
                "id" : "dec-3",
                "position" : "source",
                "y_pos" : -10,
                "class_name" : "linkStartImage"
              }, {
                "image" : "/data-intg/flows/graphics/flows/link-marking--auto-partitioning.svg",
                "temporary" : false,
                "outline" : false,
                "distance" : 2,
                "width" : 50,
                "tooltip" : "Auto-partition",
                "x_pos" : -15,
                "id" : "dec-6R",
                "position" : "middle",
                "y_pos" : 4,
                "height" : 50
              }, {
                "temporary" : false,
                "label_single_line" : true,
                "label_align" : "center",
                "tooltip" : "factfinance",
                "x_pos" : 0,
                "label" : "factfinance",
                "label_allow_return_key" : "save",
                "width" : 107,
                "label_editable" : true,
                "id" : "dec-8",
                "position" : "middle",
                "y_pos" : -20,
                "height" : 20
              } ],
              "class_name" : "linkStyle__runMetricsLinkDefaultStyle___ixW31"
            }
          },
          "link_name" : "factfinance",
          "port_id_ref" : "f9aeb68a-7615-45f8-8740-ffa034a3a13d"
        } ],
        "id" : "4bd0f0bc-fe53-4a32-8810-cd717a8cd9bf",
        "app_data" : {
          "datastage" : { },
          "ui_data" : {
            "label" : "inPort",
            "cardinality" : {
              "min" : 2,
              "max" : 2147483646
            }
          }
        },
        "schema_ref" : "71d9ca04-e4f0-4332-9bc7-b2b398c534e0",
        "parameters" : {
          "part_coll" : "part_type",
          "runtime_column_propagation" : 0
        }
      } ],
      "id" : "1c9b194c-ca7a-4a92-a0bf-d8f3b2529200",
      "type" : "execution_node",
      "app_data" : {
        "datastage" : {
          "inputs_order" : "4b4f5d6b-89bb-41ff-8ea5-c21beda8f278|4bd0f0bc-fe53-4a32-8810-cd717a8cd9bf",
          "outputs_order" : "cf94dfd4-f02c-4a94-8920-9e010fc24665"
        },
        "ui_data" : {
          "image" : "/data-intg/flows/graphics/palette/PxJoin.svg",
          "x_pos" : 269.28,
          "label" : "jiSaleskey",
          "y_pos" : 142.56
        }
      },
      "parameters" : {
        "keyProperties" : [ {
          "key" : "saleskey"
        } ],
        "output_count" : 1,
        "input_count" : 2,
        "allow_column_mapping" : false,
        "operator" : "innerjoin"
      }
    }, {
      "outputs" : [ {
        "id" : "f9aeb68a-7615-45f8-8740-ffa034a3a13d",
        "app_data" : {
          "datastage" : {
            "is_source_of_link" : "10734b55-e718-49a2-a43b-d5ddfb209481"
          },
          "ui_data" : {
            "label" : "outPort",
            "cardinality" : {
              "min" : 0,
              "max" : 2147483647
            }
          },
          "additionalProperties" : {
            "enableAcp" : true
          }
        },
        "schema_ref" : "71d9ca04-e4f0-4332-9bc7-b2b398c534e0",
        "parameters" : {
          "reject_uses" : "rows",
          "buf_free_run" : 50,
          "buf_mode" : "default",
          "queue_upper_size" : 0,
          "max_mem_buf_size" : 3145728,
          "reject_number" : 0,
          "disk_write_inc" : 1048576
        }
      } ],
      "op" : "ODBCConnectorPX",
      "connection" : {
        "ref" : "72f937ae-333f-4dbe-a518-1598956e3868",
        "properties" : {
          "currentOutputLinkType" : "PRIMARY",
          "sql.select_statement.tables.table" : "",
          "session.isolation_level" : "read_uncommitted",
          "transaction.end_of_wave" : "none",
          "outputAcpShouldHide" : true,
          "enableSchemalessDesign" : false,
          "session.autocommit_mode" : "off",
          "node_number" : 0,
          "session.code_page" : "default",
          "node_count" : 1,
          "sql.select_statement.read_statement_from_file" : false,
          "sql.select_statement.where_clause" : "",
          "sql.select_statement.columns.column" : "",
          "session.pass_lob_locator" : false,
          "limit_rows" : false,
          "session.schema_reconciliation.fail_on_size_mismatch" : true,
          "enableFlowAcpControl" : true,
          "sql.select_statement" : "select saleskey,revenue,cost,profit,datekey\nfrom em.factfinance\nwhere \ndatekey >= #datekey_start# and datekey <= #datekey_end#",
          "session.array_size" : 2000,
          "sql.enable_partitioning" : false,
          "session.schema_reconciliation.fail_on_type_mismatch" : true,
          "before_after" : false,
          "generate_sql" : false,
          "transaction.record_count" : 2000,
          "enable_quoted_i_ds" : false
        },
        "name" : "RDS postgres-dev_cp4d"
      },
      "id" : "74315f23-5ba2-444a-8f0b-e15d5455dfc6",
      "type" : "binding",
      "app_data" : {
        "datastage" : { },
        "ui_data" : {
          "image" : "/data-intg/flows/graphics/palette/ODBCConnectorPX.svg",
          "x_pos" : 47.519999999999996,
          "label" : "odbcFactfinance",
          "y_pos" : 237.6
        }
      },
      "parameters" : {
        "combinability" : "auto",
        "output_count" : 1,
        "input_count" : 0,
        "execmode" : "default_par",
        "preserve" : -3,
        "allow_column_mapping" : false
      }
    }, {
      "outputs" : [ {
        "id" : "61c2e0b0-d713-419f-9de0-df1fa2ee2f41",
        "app_data" : {
          "datastage" : {
            "is_source_of_link" : "ac9868e7-c863-48e3-8ca3-a6ec0363ffd9"
          },
          "ui_data" : {
            "label" : "outPort",
            "cardinality" : {
              "min" : 1,
              "max" : 1
            }
          }
        },
        "schema_ref" : "f33ae827-e440-457e-8266-2d820646724b",
        "parameters" : {
          "valueDerivation" : [ {
            "parsedExpression" : "Sum(facts.quantitysold)",
            "columnName" : "totalquantitysold",
            "sourceColumn" : "facts.quantitysold"
          }, {
            "parsedExpression" : "Sum(facts.cost)",
            "columnName" : "totalcost",
            "sourceColumn" : "facts.cost"
          }, {
            "parsedExpression" : "Sum(facts.revenue)",
            "columnName" : "totalrevenue",
            "sourceColumn" : "facts.revenue"
          }, {
            "parsedExpression" : "Sum(facts.profit)",
            "columnName" : "totalprofit",
            "sourceColumn" : "facts.profit"
          }, {
            "parsedExpression" : "Sum(facts.salestotal)",
            "columnName" : "totalsalesamount",
            "sourceColumn" : "facts.salestotal"
          } ],
          "buf_free_run" : 50,
          "queue_upper_size" : 0,
          "max_mem_buf_size" : 3145728,
          "disk_write_inc" : 1048576
        }
      } ],
      "op" : "PxAggregator",
      "inputs" : [ {
        "links" : [ {
          "node_id_ref" : "1c9b194c-ca7a-4a92-a0bf-d8f3b2529200",
          "type_attr" : "PRIMARY",
          "id" : "d0577937-2356-40b4-aeba-dd3d09262718",
          "app_data" : {
            "datastage" : { },
            "ui_data" : {
              "decorations" : [ {
                "image" : "/data-intg/flows/graphics/flows/link-output-handle--default-selected.svg",
                "temporary" : false,
                "outline" : false,
                "distance" : 0,
                "x_pos" : -10,
                "id" : "dec-3",
                "position" : "source",
                "y_pos" : -10,
                "class_name" : "linkStartImage"
              }, {
                "image" : "/data-intg/flows/graphics/flows/link-marking--auto-partitioning.svg",
                "temporary" : false,
                "outline" : false,
                "distance" : 2,
                "width" : 50,
                "tooltip" : "Auto-partition",
                "x_pos" : -15,
                "id" : "dec-6R",
                "position" : "middle",
                "y_pos" : 4,
                "height" : 50
              }, {
                "temporary" : false,
                "label_single_line" : true,
                "label_align" : "center",
                "tooltip" : "facts",
                "x_pos" : 0,
                "label" : "facts",
                "label_allow_return_key" : "save",
                "width" : 127,
                "label_editable" : true,
                "id" : "dec-8",
                "position" : "middle",
                "y_pos" : -20,
                "height" : 20
              } ],
              "class_name" : "linkStyle__runMetricsLinkDefaultStyle___ixW31"
            }
          },
          "link_name" : "facts",
          "port_id_ref" : "cf94dfd4-f02c-4a94-8920-9e010fc24665"
        } ],
        "id" : "72872d94-a797-4304-9421-04225d3ce25d",
        "app_data" : {
          "datastage" : { },
          "ui_data" : {
            "label" : "inPort",
            "cardinality" : {
              "min" : 1,
              "max" : 1
            }
          }
        },
        "schema_ref" : "af46f22d-697d-411f-8808-72870504e1d8",
        "parameters" : {
          "part_coll" : "part_type",
          "runtime_column_propagation" : 0
        }
      } ],
      "id" : "0969020f-dcac-4c46-96ad-355324c25f49",
      "type" : "execution_node",
      "app_data" : {
        "datastage" : { },
        "ui_data" : {
          "image" : "/data-intg/flows/graphics/palette/PxAggregator.svg",
          "x_pos" : 506.88,
          "label" : "agFacts",
          "y_pos" : 142.56
        }
      },
      "parameters" : {
        "keyProperties" : [ {
          "key" : "datekey"
        }, {
          "key" : "productkey"
        } ],
        "method" : "hash",
        "selection" : "reduce",
        "output_count" : 1,
        "nul_res" : " ",
        "input_count" : 1,
        "allow_column_mapping" : false,
        "reduceProperties" : [ [ {
          "reduce" : "quantitysold"
        }, {
          "sum" : "totalquantitysold"
        } ], [ {
          "reduce" : "cost"
        }, {
          "sum" : "totalcost",
          "decimal" : "15,2"
        } ], [ {
          "reduce" : "revenue"
        }, {
          "sum" : "totalrevenue",
          "decimal" : "15,2"
        } ], [ {
          "reduce" : "profit"
        }, {
          "sum" : "totalprofit",
          "decimal" : "15,2"
        } ], [ {
          "reduce" : "salestotal"
        }, {
          "sum" : "totalsalesamount",
          "decimal" : "15,2"
        } ] ]
      }
    }, {
      "outputs" : [ {
        "id" : "",
        "app_data" : {
          "ui_data" : {
            "label" : "outPort",
            "cardinality" : {
              "min" : 0,
              "max" : 1
            }
          }
        }
      } ],
      "op" : "PxDataSet",
      "inputs" : [ {
        "links" : [ {
          "node_id_ref" : "0969020f-dcac-4c46-96ad-355324c25f49",
          "type_attr" : "PRIMARY",
          "id" : "ac9868e7-c863-48e3-8ca3-a6ec0363ffd9",
          "app_data" : {
            "datastage" : { },
            "ui_data" : {
              "decorations" : [ {
                "image" : "/data-intg/flows/graphics/flows/link-output-handle--default-selected.svg",
                "temporary" : false,
                "outline" : false,
                "distance" : 0,
                "x_pos" : -10,
                "id" : "dec-3",
                "position" : "source",
                "y_pos" : -10,
                "class_name" : "linkStartImage"
              }, {
                "image" : "/data-intg/flows/graphics/flows/link-marking--same-partitioning.svg",
                "temporary" : false,
                "outline" : false,
                "distance" : 0,
                "width" : 50,
                "tooltip" : "Same partition",
                "x_pos" : -15,
                "id" : "dec-9K",
                "position" : "middle",
                "y_pos" : 4,
                "height" : 50
              }, {
                "temporary" : false,
                "label_single_line" : true,
                "label_align" : "center",
                "tooltip" : "productperformance",
                "x_pos" : 0,
                "label" : "productperformance",
                "label_allow_return_key" : "save",
                "width" : 160,
                "label_editable" : true,
                "id" : "dec-8",
                "position" : "middle",
                "y_pos" : -20,
                "height" : 20
              } ],
              "class_name" : "linkStyle__runMetricsLinkDefaultStyle___ixW31"
            }
          },
          "link_name" : "productperformance",
          "port_id_ref" : "61c2e0b0-d713-419f-9de0-df1fa2ee2f41"
        } ],
        "id" : "d5084a60-3967-441d-a19f-111033da0e5f",
        "app_data" : {
          "datastage" : { },
          "ui_data" : {
            "label" : "inPort",
            "cardinality" : {
              "min" : 0,
              "max" : 1
            }
          }
        },
        "schema_ref" : "f33ae827-e440-457e-8266-2d820646724b",
        "parameters" : {
          "datasetmode" : ">| [ds",
          "dataAssetName" : "#psGlobal.ReportDir#/productperformance.ds",
          "part_type" : "same",
          "part_coll" : "part_type",
          "dataset" : "#psGlobal.ReportDir#/productperformance.ds",
          "runtime_column_propagation" : 0,
          "registerDataAsset" : false
        }
      } ],
      "id" : "142e868f-ed4d-461e-9453-683475ebbb35",
      "type" : "binding",
      "app_data" : {
        "datastage" : { },
        "ui_data" : {
          "image" : "/data-intg/flows/graphics/palette/PxDataSet.svg",
          "x_pos" : 792,
          "label" : "dsProductperformanceDs",
          "y_pos" : 142.56
        }
      },
      "parameters" : {
        "output_count" : 0,
        "input_count" : 1,
        "allow_column_mapping" : false
      }
    } ],
    "description" : "Prepare data for load to Product Performance table",
    "id" : "686918f2-9822-4222-972e-f0a0bf716afe",
    "app_data" : {
      "datastage" : {
        "nls_map_name" : "UTF-8",
        "runtime_column_propagation" : "false",
        "nls_locale" : "OFF"
      },
      "ui_data" : {
        "comments" : [ ]
      }
    },
    "runtime_ref" : "pxOsh"
  } ],
  "runtimes" : [ {
    "name" : "pxOsh",
    "id" : "pxOsh"
  } ],
  "external_paramsets" : [ {
    "ref" : "4da873ac-c93b-4cae-92af-07758f3ff4c0",
    "name" : "psGlobal"
  }, {
    "ref" : "d4e99c1a-1c73-4f60-8123-0bdac5e94f0f",
    "name" : "psDatabaseConnect"
  } ],
  "json_schema" : "https://api.dataplatform.ibm.com/schemas/common-pipeline/pipeline-flow/pipeline-flow-v3-schema.json",
  "schemas" : [ {
    "id" : "5bb144de-ef15-418b-9d13-e9aa5c756f0c",
    "fields" : [ {
      "metadata" : {
        "item_index" : 0,
        "is_key" : true,
        "min_length" : 0,
        "decimal_scale" : 0,
        "decimal_precision" : 0,
        "description" : "<none>\r\nSearchable? N ",
        "max_length" : 10,
        "is_signed" : true
      },
      "nullable" : false,
      "name" : "saleskey",
      "type" : "integer",
      "app_data" : {
        "column_reference" : "saleskey",
        "time_scale" : 0,
        "odbc_type" : "INTEGER",
        "apt_field_properties" : "quote=none",
        "table_def" : "ODBC-postgreSQL-ww2_117.factsales",
        "array_handling" : 0,
        "is_unicode_string" : false,
        "type_code" : "INT32"
      }
    }, {
      "metadata" : {
        "item_index" : 0,
        "is_key" : false,
        "min_length" : 0,
        "decimal_scale" : 0,
        "decimal_precision" : 0,
        "description" : "<none>\r\nSearchable? N ",
        "max_length" : 10,
        "is_signed" : true
      },
      "nullable" : true,
      "name" : "productkey",
      "type" : "integer",
      "app_data" : {
        "column_reference" : "productkey",
        "time_scale" : 0,
        "odbc_type" : "INTEGER",
        "apt_field_properties" : "quote=none, null_field=''",
        "table_def" : "ODBC-postgreSQL-ww2_117.factsales",
        "array_handling" : 0,
        "is_unicode_string" : false,
        "type_code" : "INT32"
      }
    }, {
      "metadata" : {
        "item_index" : 0,
        "is_key" : false,
        "min_length" : 0,
        "decimal_scale" : 0,
        "decimal_precision" : 0,
        "description" : "<none>\r\nSearchable? N ",
        "max_length" : 10,
        "is_signed" : true
      },
      "nullable" : true,
      "name" : "quantitysold",
      "type" : "integer",
      "app_data" : {
        "column_reference" : "quantitysold",
        "time_scale" : 0,
        "odbc_type" : "INTEGER",
        "apt_field_properties" : "quote=none, null_field=''",
        "table_def" : "ODBC-postgreSQL-ww2_117.factsales",
        "array_handling" : 0,
        "is_unicode_string" : false,
        "type_code" : "INT32"
      }
    }, {
      "metadata" : {
        "item_index" : 0,
        "is_key" : false,
        "min_length" : 0,
        "decimal_scale" : 2,
        "decimal_precision" : 10,
        "description" : "<none>\r\nSearchable? N ",
        "max_length" : 10,
        "is_signed" : false
      },
      "nullable" : true,
      "name" : "salestotal",
      "type" : "double",
      "app_data" : {
        "column_reference" : "salestotal",
        "time_scale" : 0,
        "odbc_type" : "NUMERIC",
        "apt_field_properties" : "quote=none, null_field=''",
        "table_def" : "ODBC-postgreSQL-ww2_117.factsales",
        "array_handling" : 0,
        "is_unicode_string" : false,
        "type_code" : "DECIMAL"
      }
    } ]
  }, {
    "id" : "af46f22d-697d-411f-8808-72870504e1d8",
    "fields" : [ {
      "metadata" : {
        "item_index" : 0,
        "is_key" : false,
        "min_length" : 0,
        "decimal_scale" : 0,
        "decimal_precision" : 0,
        "description" : "<none>\r\nSearchable? N ",
        "source_field_id" : "factsales.productkey",
        "max_length" : 10,
        "is_signed" : true
      },
      "nullable" : true,
      "name" : "productkey",
      "type" : "integer",
      "app_data" : {
        "time_scale" : 0,
        "odbc_type" : "INTEGER",
        "apt_field_properties" : "quote=none, null_field=''",
        "array_handling" : 0,
        "is_unicode_string" : false,
        "type_code" : "INT32"
      }
    }, {
      "metadata" : {
        "item_index" : 0,
        "is_key" : false,
        "min_length" : 0,
        "decimal_scale" : 0,
        "decimal_precision" : 0,
        "description" : "<none>\r\nSearchable? N ",
        "source_field_id" : "factsales.quantitysold",
        "max_length" : 10,
        "is_signed" : true
      },
      "nullable" : true,
      "name" : "quantitysold",
      "type" : "integer",
      "app_data" : {
        "time_scale" : 0,
        "odbc_type" : "INTEGER",
        "apt_field_properties" : "quote=none, null_field=''",
        "array_handling" : 0,
        "is_unicode_string" : false,
        "type_code" : "INT32"
      }
    }, {
      "metadata" : {
        "item_index" : 0,
        "is_key" : false,
        "min_length" : 0,
        "decimal_scale" : 2,
        "decimal_precision" : 10,
        "description" : "<none>\r\nSearchable? N ",
        "source_field_id" : "factsales.salestotal",
        "max_length" : 10,
        "is_signed" : false
      },
      "nullable" : true,
      "name" : "salestotal",
      "type" : "double",
      "app_data" : {
        "time_scale" : 0,
        "odbc_type" : "NUMERIC",
        "apt_field_properties" : "quote=none, null_field=''",
        "array_handling" : 0,
        "is_unicode_string" : false,
        "type_code" : "DECIMAL"
      }
    }, {
      "metadata" : {
        "item_index" : 0,
        "is_key" : false,
        "min_length" : 0,
        "decimal_scale" : 2,
        "decimal_precision" : 10,
        "description" : "<none>\r\nSearchable? N ",
        "source_field_id" : "factfinance.revenue",
        "max_length" : 10,
        "is_signed" : false
      },
      "nullable" : true,
      "name" : "revenue",
      "type" : "double",
      "app_data" : {
        "time_scale" : 0,
        "odbc_type" : "NUMERIC",
        "apt_field_properties" : "quote=none, null_field=''",
        "array_handling" : 0,
        "is_unicode_string" : false,
        "type_code" : "DECIMAL"
      }
    }, {
      "metadata" : {
        "item_index" : 0,
        "is_key" : false,
        "min_length" : 0,
        "decimal_scale" : 2,
        "decimal_precision" : 10,
        "description" : "<none>\r\nSearchable? N ",
        "source_field_id" : "factfinance.cost",
        "max_length" : 10,
        "is_signed" : false
      },
      "nullable" : true,
      "name" : "cost",
      "type" : "double",
      "app_data" : {
        "time_scale" : 0,
        "odbc_type" : "NUMERIC",
        "apt_field_properties" : "quote=none, null_field=''",
        "array_handling" : 0,
        "is_unicode_string" : false,
        "type_code" : "DECIMAL"
      }
    }, {
      "metadata" : {
        "item_index" : 0,
        "is_key" : false,
        "min_length" : 0,
        "decimal_scale" : 2,
        "decimal_precision" : 10,
        "description" : "<none>\r\nSearchable? N ",
        "source_field_id" : "factfinance.profit",
        "max_length" : 10,
        "is_signed" : false
      },
      "nullable" : true,
      "name" : "profit",
      "type" : "double",
      "app_data" : {
        "time_scale" : 0,
        "odbc_type" : "NUMERIC",
        "apt_field_properties" : "quote=none, null_field=''",
        "array_handling" : 0,
        "is_unicode_string" : false,
        "type_code" : "DECIMAL"
      }
    }, {
      "metadata" : {
        "item_index" : 0,
        "is_key" : false,
        "min_length" : 0,
        "decimal_scale" : 0,
        "decimal_precision" : 0,
        "description" : "<none>\r\nSearchable? N ",
        "source_field_id" : "factfinance.datekey",
        "max_length" : 10,
        "is_signed" : true
      },
      "nullable" : true,
      "name" : "datekey",
      "type" : "integer",
      "app_data" : {
        "time_scale" : 0,
        "odbc_type" : "INTEGER",
        "apt_field_properties" : "quote=none, null_field=''",
        "array_handling" : 0,
        "is_unicode_string" : false,
        "type_code" : "INT32"
      }
    }, {
      "metadata" : {
        "item_index" : 0,
        "is_key" : true,
        "min_length" : 0,
        "decimal_scale" : 0,
        "decimal_precision" : 0,
        "description" : "<none>\r\nSearchable? N ",
        "source_field_id" : "factsales.saleskey",
        "max_length" : 10,
        "is_signed" : true
      },
      "nullable" : false,
      "name" : "saleskey",
      "type" : "integer",
      "app_data" : {
        "time_scale" : 0,
        "odbc_type" : "INTEGER",
        "apt_field_properties" : "quote=none",
        "array_handling" : 0,
        "is_unicode_string" : false,
        "type_code" : "INT32"
      }
    } ]
  }, {
    "id" : "71d9ca04-e4f0-4332-9bc7-b2b398c534e0",
    "fields" : [ {
      "metadata" : {
        "item_index" : 0,
        "is_key" : false,
        "min_length" : 0,
        "decimal_scale" : 0,
        "decimal_precision" : 0,
        "description" : "<none>\r\nSearchable? N ",
        "max_length" : 10,
        "is_signed" : true
      },
      "nullable" : true,
      "name" : "saleskey",
      "type" : "integer",
      "app_data" : {
        "column_reference" : "saleskey",
        "time_scale" : 0,
        "odbc_type" : "INTEGER",
        "apt_field_properties" : "quote=none, null_field=''",
        "table_def" : "ODBC-postgreSQL-ww2_117.factfinance",
        "array_handling" : 0,
        "is_unicode_string" : false,
        "type_code" : "INT32"
      }
    }, {
      "metadata" : {
        "item_index" : 0,
        "is_key" : false,
        "min_length" : 0,
        "decimal_scale" : 2,
        "decimal_precision" : 10,
        "description" : "<none>\r\nSearchable? N ",
        "max_length" : 10,
        "is_signed" : false
      },
      "nullable" : true,
      "name" : "revenue",
      "type" : "double",
      "app_data" : {
        "column_reference" : "revenue",
        "time_scale" : 0,
        "odbc_type" : "NUMERIC",
        "apt_field_properties" : "quote=none, null_field=''",
        "table_def" : "ODBC-postgreSQL-ww2_117.factfinance",
        "array_handling" : 0,
        "is_unicode_string" : false,
        "type_code" : "DECIMAL"
      }
    }, {
      "metadata" : {
        "item_index" : 0,
        "is_key" : false,
        "min_length" : 0,
        "decimal_scale" : 2,
        "decimal_precision" : 10,
        "description" : "<none>\r\nSearchable? N ",
        "max_length" : 10,
        "is_signed" : false
      },
      "nullable" : true,
      "name" : "cost",
      "type" : "double",
      "app_data" : {
        "column_reference" : "cost",
        "time_scale" : 0,
        "odbc_type" : "NUMERIC",
        "apt_field_properties" : "quote=none, null_field=''",
        "table_def" : "ODBC-postgreSQL-ww2_117.factfinance",
        "array_handling" : 0,
        "is_unicode_string" : false,
        "type_code" : "DECIMAL"
      }
    }, {
      "metadata" : {
        "item_index" : 0,
        "is_key" : false,
        "min_length" : 0,
        "decimal_scale" : 2,
        "decimal_precision" : 10,
        "description" : "<none>\r\nSearchable? N ",
        "max_length" : 10,
        "is_signed" : false
      },
      "nullable" : true,
      "name" : "profit",
      "type" : "double",
      "app_data" : {
        "column_reference" : "profit",
        "time_scale" : 0,
        "odbc_type" : "NUMERIC",
        "apt_field_properties" : "quote=none, null_field=''",
        "table_def" : "ODBC-postgreSQL-ww2_117.factfinance",
        "array_handling" : 0,
        "is_unicode_string" : false,
        "type_code" : "DECIMAL"
      }
    }, {
      "metadata" : {
        "item_index" : 0,
        "is_key" : false,
        "min_length" : 0,
        "decimal_scale" : 0,
        "decimal_precision" : 0,
        "description" : "<none>\r\nSearchable? N ",
        "max_length" : 10,
        "is_signed" : true
      },
      "nullable" : true,
      "name" : "datekey",
      "type" : "integer",
      "app_data" : {
        "column_reference" : "datekey",
        "time_scale" : 0,
        "odbc_type" : "INTEGER",
        "apt_field_properties" : "quote=none, null_field=''",
        "table_def" : "ODBC-postgreSQL-ww2_117.factfinance",
        "array_handling" : 0,
        "is_unicode_string" : false,
        "type_code" : "INT32"
      }
    } ]
  }, {
    "id" : "f33ae827-e440-457e-8266-2d820646724b",
    "fields" : [ {
      "metadata" : {
        "item_index" : 0,
        "is_key" : false,
        "min_length" : 0,
        "decimal_scale" : 0,
        "decimal_precision" : 0,
        "description" : "<none>\r\nSearchable? N ",
        "source_field_id" : "facts.datekey",
        "max_length" : 10,
        "is_signed" : true
      },
      "nullable" : true,
      "name" : "datekey",
      "type" : "integer",
      "app_data" : {
        "column_reference" : "datekey",
        "odbc_type" : "INTEGER",
        "apt_field_properties" : "quote=none, null_field=''",
        "table_def" : "ODBC-postgreSQL-ww2_117.factfinance",
        "array_handling" : 0,
        "is_unicode_string" : false,
        "type_code" : "INT32"
      }
    }, {
      "metadata" : {
        "item_index" : 0,
        "is_key" : false,
        "min_length" : 0,
        "decimal_scale" : 0,
        "decimal_precision" : 0,
        "description" : "<none>\r\nSearchable? N ",
        "source_field_id" : "facts.productkey",
        "max_length" : 10,
        "is_signed" : true
      },
      "nullable" : true,
      "name" : "productkey",
      "type" : "integer",
      "app_data" : {
        "column_reference" : "productkey",
        "odbc_type" : "INTEGER",
        "apt_field_properties" : "quote=none, null_field=''",
        "table_def" : "ODBC-postgreSQL-ww2_117.factsales",
        "array_handling" : 0,
        "is_unicode_string" : false,
        "type_code" : "INT32"
      }
    }, {
      "metadata" : {
        "item_index" : 0,
        "is_key" : false,
        "min_length" : 0,
        "decimal_scale" : 0,
        "decimal_precision" : 0,
        "max_length" : 0,
        "is_signed" : false
      },
      "nullable" : true,
      "name" : "totalquantitysold",
      "type" : "double",
      "app_data" : {
        "odbc_type" : "DOUBLE",
        "array_handling" : 0,
        "is_unicode_string" : false,
        "type_code" : "DFLOAT"
      }
    }, {
      "metadata" : {
        "item_index" : 0,
        "is_key" : false,
        "min_length" : 0,
        "decimal_scale" : 2,
        "decimal_precision" : 15,
        "max_length" : 15,
        "is_signed" : false
      },
      "nullable" : true,
      "name" : "totalcost",
      "type" : "double",
      "app_data" : {
        "odbc_type" : "DECIMAL",
        "array_handling" : 0,
        "is_unicode_string" : false,
        "type_code" : "DECIMAL"
      }
    }, {
      "metadata" : {
        "item_index" : 0,
        "is_key" : false,
        "min_length" : 0,
        "decimal_scale" : 2,
        "decimal_precision" : 15,
        "max_length" : 15,
        "is_signed" : false
      },
      "nullable" : true,
      "name" : "totalrevenue",
      "type" : "double",
      "app_data" : {
        "odbc_type" : "DECIMAL",
        "array_handling" : 0,
        "is_unicode_string" : false,
        "type_code" : "DECIMAL"
      }
    }, {
      "metadata" : {
        "item_index" : 0,
        "is_key" : false,
        "min_length" : 0,
        "decimal_scale" : 2,
        "decimal_precision" : 15,
        "max_length" : 15,
        "is_signed" : false
      },
      "nullable" : true,
      "name" : "totalprofit",
      "type" : "double",
      "app_data" : {
        "odbc_type" : "DECIMAL",
        "array_handling" : 0,
        "is_unicode_string" : false,
        "type_code" : "DECIMAL"
      }
    }, {
      "metadata" : {
        "item_index" : 0,
        "is_key" : false,
        "min_length" : 0,
        "decimal_scale" : 2,
        "decimal_precision" : 15,
        "max_length" : 15,
        "is_signed" : false
      },
      "nullable" : true,
      "name" : "totalsalesamount",
      "type" : "double",
      "app_data" : {
        "odbc_type" : "DECIMAL",
        "array_handling" : 0,
        "is_unicode_string" : false,
        "type_code" : "DECIMAL"
      }
    } ]
  } ],
  "doc_type" : "pipeline",
  "id" : "196c3b53-ed02-48fd-991a-8b8e2a0ec4ba",
  "app_data" : {
    "datastage" : {
      "timestamp_format" : "%yyyy-%mm-%dd %hh:%nn:%ss",
      "decimal_separator" : ".",
      "flowRunPriorityQueue" : "Medium",
      "time_format" : "%hh:%nn:%ss",
      "external_message_handlers" : [ ],
      "date_format" : "%yyyy-%mm-%dd",
      "message_handlers" : [ ],
      "version" : "3.0.5"
    },
    "additionalProperties" : {
      "transInputLinkMapper" : { },
      "ELTDropdown" : {
        "id" : "nesting",
        "label" : "Generate nested SQL",
        "value" : "NESTED_QUERY"
      },
      "saveChangeFrequency" : "apply_changes_temporarily",
      "disableParamsCacheOnFlow" : false,
      "rcpLinkList" : [ ],
      "globalAcp" : true,
      "enableRCP" : false,
      "isNewTransActive" : false,
      "enableSchemaLessDesign" : false,
      "runMode" : "ETL"
    }
  },
  "version" : "3.0",
  "parameters" : {
    "local_parameters" : [ {
      "subtype" : "",
      "name" : "datekey_start",
      "type" : "int64",
      "prompt" : "start date",
      "value" : 20230101
    }, {
      "subtype" : "",
      "name" : "datekey_end",
      "type" : "int64",
      "prompt" : "end date",
      "value" : 20240831
    } ]
  }
}